[
    {
        "keyword": "sample",
        "translate": "Ví dụ",
        "paragraph_english": "Doctors will take a sample of your blood",
        "paragraph_vietnamese": "Bác sĩ sẽ lấy mẫu máu của chị",
        "phrases": [
            {
                "title": "a sample of something",
                "content": "một mẫu của một cái gì đó"
            }
        ]
    },
    {
        "keyword": "movement",
        "translate": "Phong trào",
        "paragraph_english": "A social movement can significantly shape of society",
        "paragraph_vietnamese": "Một phong trào xã hội có thể ảnh hưởng đáng kể đến một xã hội",
        "phrases": [
            {
                "title": "a social movement",
                "content": "một phong trào xã hội"
            },
            {
                "title": "significantly",
                "content": "đáng kể"
            },
            {
                "title": "shape of society",
                "content": "định hình xã hội"
            }
        ]
    },
    {
        "keyword": "revolution",
        "translate": "Cuộc cách mạng",
        "paragraph_english": "The activists started a revolution",
        "paragraph_vietnamese": "Những nhà hoạt động xã hội đã bắt đầu một cuộc cách mạng",
        "phrases": [
            {
                "title": "start a revolution",
                "content": "bắt đầu một cuộc cách mạng"
            },
            {
                "title": "the activists",
                "content": "các nhà hoạt động"
            }
        ]
    },
    {
        "keyword": "section",
        "translate": "Phần",
        "paragraph_english": "This section of the book is interesting",
        "paragraph_vietnamese": "Phần này của cuốn sách rất thú vị",
        "phrases": [
            {
                "title": "a section of something",
                "content": "một phần của một cái gì đó"
            }
        ]
    },
    {
        "keyword": "massive",
        "translate": "Ồ ạt",
        "paragraph_english": "The army launched a massive attack on the enemy",
        "paragraph_vietnamese": "Quân đội phát động một cuộc tấn công lớn vào kẻ thù",
        "phrases": [
            {
                "title": "a massive attack",
                "content": "cuộc tấn công lớn"
            },
            {
                "title": "launched",
                "content": "phát động, tung ra"
            }
        ]
    },
    {
        "keyword": "occur",
        "translate": "Xảy ra",
        "paragraph_english": "Earthquakes occur frequently in Japan",
        "paragraph_vietnamese": "Động đất xảy ra thường xuyên ở Nhật Bản",
        "phrases": [
            {
                "title": "occur frequently",
                "content": "xảy ra thường xuyên"
            }
        ]
    },
    {
        "keyword": "powerful",
        "translate": "Mạng mẽ",
        "paragraph_english": "The speaker had a powerful voice",
        "paragraph_vietnamese": "Diễn giả có một giọng nói đầy uy lực",
        "phrases": [
            {
                "title": "a powerful voice",
                "content": "một giọng nói đầy uy lực"
            }
        ]
    },
    {
        "keyword": "union",
        "translate": "Hiệp hội",
        "paragraph_english": "You can join a labor union",
        "paragraph_vietnamese": "Cậu có thể tham gia công đoàn",
        "phrases": [
            {
                "title": "labor union",
                "content": "công đoàn"
            }
        ]
    },
    {
        "keyword": "rescue",
        "translate": "Giải cứu",
        "paragraph_english": "The koala was rescued from the fire",
        "paragraph_vietnamese": "Chú gấu túi được giải cứu khỏi đám cháy",
        "phrases": [
            {
                "title": "rescue from something",
                "content": "giải cứu khỏi cái gì"
            },
            {
                "title": "koala",
                "content": "gấu túi"
            }
        ]
    },
    {
        "keyword": "force",
        "translate": "Bắt buộc",
        "paragraph_english": "They forced me to clean the dishes",
        "paragraph_vietnamese": "Họ bắt buộc tôi phải rửa bát",
        "phrases": [
            {
                "title": "force something or someone",
                "content": "bắt buộc cái gì đó hoặc ai đó"
            }
        ]
    },
    {
        "keyword": "exist",
        "translate": "tồn tại",
        "paragraph_english": "Tree exist to provide oxygen",
        "paragraph_vietnamese": "Cây tồn tại để cung cấp khí oxy",
        "phrases": [
            {
                "title": "exist to do something",
                "content": "tồn tại để làm một cái gì đó"
            }
        ]
    },
    {
        "keyword": "campaign",
        "translate": "Chiến dịch",
        "paragraph_english": "We should start a campaign to save animals",
        "paragraph_vietnamese": "Chúng ta nên bắt đầu một chiến dịch để cứu lấy các loài vật",
        "phrases": [
            {
                "title": "a campaign to do something",
                "content": "Một chiến dịch để làm cái gì đó"
            }
        ]
    },
    {
        "keyword": "election",
        "translate": "Cuộc bầu cử",
        "paragraph_english": "Citizens can vote at the national election",
        "paragraph_vietnamese": "Công dân có thể bỏ phiếu trong cuộc bầu cử toàn quốc",
        "phrases": [
            {
                "title": "national election",
                "content": "Cuộc bầu cử toàn quốc"
            },
            {
                "title": "citizen",
                "content": "Công dân"
            }
        ]
    },
    {
        "keyword": "soldier",
        "translate": "Người lính",
        "paragraph_english": "There are soldiers on duty around the embassy",
        "paragraph_vietnamese": "Có nhiều người lính đang làm nhiện vụ xung quanh đại sứ quán",
        "phrases": [
            {
                "title": "a soldier on duty",
                "content": "một người lính đang làm nhiệm vụ"
            },
            {
                "title": "embassy",
                "content": "đại sứ quán"
            }
        ]
    },
    {
        "keyword": "vote",
        "translate": "bầu chọn",
        "paragraph_english": "I voted for the new president",
        "paragraph_vietnamese": "Tôi đã bầu chọn cho tổng thống mới",
        "phrases": [
            {
                "title": "vote for somebody",
                "content": "bầu chọn cho ai đó"
            }
        ]
    },
    {
        "keyword": "army",
        "translate": "quân đội",
        "paragraph_english": "My brother is in the army",
        "paragraph_vietnamese": "Em trai tôi ở trong quân đội",
        "phrases": [
            {
                "title": "in the army",
                "content": "trong quân đội"
            }
        ]
    },
    {
        "keyword": "politics",
        "translate": "chính trị",
        "paragraph_english": "Employees should avoid office politics",
        "paragraph_vietnamese": "Nhân viên nên tránh chính trị công sở",
        "phrases": [
            {
                "title": "office politics",
                "content": "chính trị công sở"
            }
        ]
    },
    {
        "keyword": "medal",
        "translate": "huân chương",
        "paragraph_english": "She was given a Medal of Honor",
        "paragraph_vietnamese": "Cô ấy được trao một huân chương danh dự",
        "phrases": [
            {
                "title": "a Medal of Honor",
                "content": "một huân chương danh dự"
            }
        ]
    },
    {
        "keyword": "president",
        "translate": "tổng thống",
        "paragraph_english": "He is serving as acting president of the country",
        "paragraph_vietnamese": "Ông ấy đang đảm nhiệm chức vụ quyền tổng thống của đất nước",
        "phrases": [
            {
                "title": "an acting president",
                "content": "quyền tổng thống"
            },
            {
                "title": "serving",
                "content": "phục vụ, đảm nhận"
            },
            {
                "title": "the country",
                "content": "đất nước"
            }
        ]
    },
    {
        "keyword": "pilot",
        "translate": "phi công",
        "paragraph_english": "I am studying to be an airline pilot",
        "paragraph_vietnamese": "Tôi đang học làm phi công",
        "phrases": [
            {
                "title": "an airline pilot",
                "content": "một phi công hàng không"
            }
        ]
    }
]